naf/__init__.py
naf/db
france_naf-20210302.dist-info/METADATA
france_naf-20210302.dist-info/WHEEL
france_naf-20210302.dist-info/top_level.txt
france_naf-20210302.dist-info/RECORD
