Metadata-Version: 2.1
Name: france-naf
Version: 20210302
Summary: Python accessors to French NAF/APE codes
Home-page: https://github.com/pyrates/france-naf
License: MIT
Keywords: naf ape
Platform: UNKNOWN
Classifier: Development Status :: 3 - Alpha
Classifier: Intended Audience :: Developers
Classifier: License :: OSI Approved :: MIT License
Classifier: Operating System :: OS Independent
Classifier: Programming Language :: Python
Classifier: Programming Language :: Python :: 3.7
Classifier: Programming Language :: Python :: 3.8
Classifier: Programming Language :: Python :: 3.9
Provides-Extra: dev
Requires-Dist: xlrd (==1.2.0) ; extra == 'dev'
Provides-Extra: test
Requires-Dist: pytest (==6.1.1) ; extra == 'test'
